{
  "$schema": "http://json-schema.org/draft-04/schema#",
  "description": "Relinquishment response provided to a CBSD",
  "type": "object",
  "required": [ "response" ],
  "properties": {
    "cbsdId": { "type": "string",
                "description": "Unique designator for the CBSD as provided in the relinquishment request." },
    "grantId": { "type": "string",
                 "description": "Unique designator for the grant as provided in the relinquishment request." },
    "response": { "$ref": "file:Response.schema.json" }
  }
}

